README.md
setup.py
AirzoneCloudDaikin/AirzoneCloudDaikin.py
AirzoneCloudDaikin/Device.py
AirzoneCloudDaikin/Installation.py
AirzoneCloudDaikin/__init__.py
AirzoneCloudDaikin/contants.py
AirzoneCloudDaikin.egg-info/PKG-INFO
AirzoneCloudDaikin.egg-info/SOURCES.txt
AirzoneCloudDaikin.egg-info/dependency_links.txt
AirzoneCloudDaikin.egg-info/requires.txt
AirzoneCloudDaikin.egg-info/top_level.txt